{"stats":{"minecraft:mined":{"minecraft:red_mushroom":1},"minecraft:used":{"minecraft:piglin_spawn_egg":15,"infernalwar:pig_iron_leggings":1,"infernalwar:pig_iron_helmet":1,"minecraft:splash_potion":25},"minecraft:custom":{"minecraft:jump":10,"minecraft:time_since_rest":4390,"minecraft:damage_dealt":315,"minecraft:crouch_one_cm":88,"minecraft:sprint_one_cm":470,"minecraft:deaths":1,"minecraft:play_time":5040,"minecraft:damage_taken":448,"minecraft:time_since_death":4369,"minecraft:walk_one_cm":16103,"minecraft:sneak_time":48,"minecraft:total_world_time":5610,"minecraft:mob_kills":4,"minecraft:fly_one_cm":13559},"minecraft:killed":{"minecraft:zombified_piglin":2,"minecraft:piglin":2},"minecraft:killed_by":{"minecraft:piglin":1}},"DataVersion":3218}