{"stats":{"minecraft:picked_up":{"infernalwar:pig_iron_chestplate":1,"minecraft:blackstone":9,"minecraft:quartz":2,"minecraft:cracked_polished_blackstone_bricks":4,"minecraft:piglin_spawn_egg":1,"minecraft:coal":1},"minecraft:used":{"minecraft:firework_rocket":38,"minecraft:tnt":37,"minecraft:flint_and_steel":3,"minecraft:piglin_spawn_egg":53,"minecraft:wither_skeleton_spawn_egg":1,"minecraft:blue_bed":11},"minecraft:dropped":{"infernalwar:pig_iron_leggings":1,"infernalwar:pig_iron_helmet":1,"minecraft:piglin_spawn_egg":1,"infernalwar:pig_iron_boots":1,"infernalwar:pig_iron_chestplate":3},"minecraft:custom":{"minecraft:time_since_rest":12764,"minecraft:crouch_one_cm":91,"minecraft:play_time":12764,"minecraft:walk_one_cm":16353,"minecraft:sneak_time":304,"minecraft:mob_kills":6,"minecraft:drop":7,"minecraft:aviate_one_cm":304583,"minecraft:jump":51,"minecraft:damage_dealt":88,"minecraft:leave_game":1,"minecraft:time_since_death":12764,"minecraft:total_world_time":16525,"minecraft:fly_one_cm":57607}},"DataVersion":3218}