{
  "minecraft:recipes/tools/flint_and_steel": {
    "criteria": {
      "has_obsidian": "2023-03-07 00:12:48 -0600"
    },
    "done": true
  },
  "minecraft:recipes/tools/golden_hoe": {
    "criteria": {
      "has_gold_ingot": "2023-03-07 00:14:18 -0600"
    },
    "done": true
  },
  "minecraft:recipes/misc/gold_ingot_from_nuggets": {
    "criteria": {
      "has_gold_nugget": "2023-03-07 00:14:00 -0600"
    },
    "done": true
  },
  "minecraft:recipes/combat/golden_sword": {
    "criteria": {
      "has_gold_ingot": "2023-03-07 00:14:18 -0600"
    },
    "done": true
  },
  "minecraft:recipes/food/golden_apple": {
    "criteria": {
      "has_gold_ingot": "2023-03-07 00:14:18 -0600"
    },
    "done": true
  },
  "minecraft:end/elytra": {
    "criteria": {
      "elytra": "2023-03-07 00:07:13 -0600"
    },
    "done": true
  },
  "minecraft:recipes/tools/golden_pickaxe": {
    "criteria": {
      "has_gold_ingot": "2023-03-07 00:14:18 -0600"
    },
    "done": true
  },
  "minecraft:story/enter_the_nether": {
    "criteria": {
      "entered_nether": "2023-03-07 00:13:09 -0600"
    },
    "done": true
  },
  "minecraft:recipes/decorations/enchanting_table": {
    "criteria": {
      "has_obsidian": "2023-03-07 00:12:48 -0600"
    },
    "done": true
  },
  "minecraft:recipes/misc/gold_nugget": {
    "criteria": {
      "has_gold_ingot": "2023-03-07 00:14:18 -0600"
    },
    "done": true
  },
  "minecraft:recipes/building_blocks/gold_block": {
    "criteria": {
      "has_gold_ingot": "2023-03-07 00:14:18 -0600"
    },
    "done": true
  },
  "minecraft:recipes/tools/golden_axe": {
    "criteria": {
      "has_gold_ingot": "2023-03-07 00:14:18 -0600"
    },
    "done": true
  },
  "minecraft:recipes/combat/golden_chestplate": {
    "criteria": {
      "has_gold_ingot": "2023-03-07 00:14:18 -0600"
    },
    "done": true
  },
  "minecraft:recipes/brewing/golden_carrot": {
    "criteria": {
      "has_gold_nugget": "2023-03-07 00:14:00 -0600"
    },
    "done": true
  },
  "minecraft:recipes/combat/golden_leggings": {
    "criteria": {
      "has_gold_ingot": "2023-03-07 00:14:18 -0600"
    },
    "done": true
  },
  "minecraft:recipes/combat/golden_helmet": {
    "criteria": {
      "has_gold_ingot": "2023-03-07 00:14:18 -0600"
    },
    "done": true
  },
  "minecraft:nether/root": {
    "criteria": {
      "entered_nether": "2023-03-07 00:13:09 -0600"
    },
    "done": true
  },
  "minecraft:nether/find_bastion": {
    "criteria": {
      "bastion": "2023-03-07 00:09:37 -0600"
    },
    "done": true
  },
  "minecraft:story/form_obsidian": {
    "criteria": {
      "obsidian": "2023-03-07 00:12:48 -0600"
    },
    "done": true
  },
  "minecraft:recipes/redstone/light_weighted_pressure_plate": {
    "criteria": {
      "has_gold_ingot": "2023-03-07 00:14:18 -0600"
    },
    "done": true
  },
  "minecraft:nether/explore_nether": {
    "criteria": {
      "minecraft:crimson_forest": "2023-03-07 00:07:15 -0600",
      "minecraft:nether_wastes": "2023-03-07 00:13:46 -0600",
      "minecraft:basalt_deltas": "2023-03-07 00:15:00 -0600",
      "minecraft:warped_forest": "2023-03-07 00:13:10 -0600"
    },
    "done": false
  },
  "minecraft:recipes/tools/golden_shovel": {
    "criteria": {
      "has_gold_ingot": "2023-03-07 00:14:18 -0600"
    },
    "done": true
  },
  "minecraft:recipes/combat/golden_boots": {
    "criteria": {
      "has_gold_ingot": "2023-03-07 00:14:18 -0600"
    },
    "done": true
  },
  "DataVersion": 3218
}